Metadata-Version: 2.2
Name: tc_aws
Version: 7.0.4
Summary: Thumbor AWS extensions
Author: Thumbor-Community & William King
Author-email: h.briand@gmail.com
Keywords: thumbor aws
Classifier: Development Status :: 5 - Production/Stable
Classifier: Intended Audience :: Developers
Classifier: License :: OSI Approved :: MIT License
Classifier: Operating System :: OS Independent
Classifier: Topic :: Software Development :: Libraries :: Python Modules
Classifier: Topic :: Internet
Classifier: Programming Language :: Python :: 3
Classifier: Programming Language :: Python :: 3.6
Classifier: Programming Language :: Python :: 3.7
Classifier: Programming Language :: Python :: 3.8
License-File: LICENSE
Requires-Dist: python-dateutil<2.9,>=2.8
Requires-Dist: thumbor<8,>=7.0.0a2
Requires-Dist: aiobotocore==2.23.0
Requires-Dist: boto3<1.39.0,>=1.38.0
Provides-Extra: tests
Requires-Dist: coverage<8,>=7; extra == "tests"
Requires-Dist: moto[server]<6.0.0,>=5.0.0; extra == "tests"
Requires-Dist: mock<6.0,>=5.0; extra == "tests"
Requires-Dist: pytest<9.0,>=8.4; extra == "tests"
Dynamic: author
Dynamic: author-email
Dynamic: classifier
Dynamic: description
Dynamic: description-content-type
Dynamic: keywords
Dynamic: provides-extra
Dynamic: requires-dist
Dynamic: summary
